dbus_notification/__init__.py
dbus_notification/__main__.py
dbus_notification-2025.5.0.dist-info/LICENSE.md
dbus_notification-2025.5.0.dist-info/METADATA
dbus_notification-2025.5.0.dist-info/WHEEL
dbus_notification-2025.5.0.dist-info/entry_points.txt
dbus_notification-2025.5.0.dist-info/top_level.txt
dbus_notification-2025.5.0.dist-info/RECORD
